biogeoloc/__init__.py
biogeoloc/cls.py
biogeoloc/genesys.py
biogeoloc/versions.py
biogeoloc-0.0.4.dist-info/LICENSE
biogeoloc-0.0.4.dist-info/METADATA
biogeoloc-0.0.4.dist-info/WHEEL
biogeoloc-0.0.4.dist-info/top_level.txt
biogeoloc-0.0.4.dist-info/RECORD
