Metadata-Version: 2.1
Name: biogeoloc
Version: 0.0.4
Summary: A python object package for storing and managing geographic information about biological samples.
Home-page: https://github.com/SouthernCD/biogeoloc
Author: Yuxing Xu
Author-email: xuyuxing@mail.kib.ac.cn
Requires-Python: >=3.5
License-File: LICENSE
Requires-Dist: yxmath
Requires-Dist: yxmap
Requires-Dist: yxutil
Requires-Dist: pandas
Requires-Dist: numpy
